pyswyfter/__init__.py
pyswyfter/loaders.py
pyswyfter/timer.py
pyswyfter/vars.py
pyswyfter/decorators/__init__.py
pyswyfter/decorators/actions.py
pyswyfter/decorators/auth.py
pyswyfter/decorators/validators.py
pyswyfter/utils/__init__.py
pyswyfter/utils/strings.py
pyswyfter/validators/__init__.py
pyswyfter/validators/ivalidators.py
pyswyfter/validators/misc.py
pyswyfter-0.3.1.dist-info/LICENSE
pyswyfter-0.3.1.dist-info/METADATA
pyswyfter-0.3.1.dist-info/WHEEL
pyswyfter-0.3.1.dist-info/top_level.txt
pyswyfter-0.3.1.dist-info/RECORD
